l0n0lhttputils/__init__.py
l0n0lhttputils/config_file.py
l0n0lhttputils/dbmysql.py
l0n0lhttputils/http_server.py
l0n0lhttputils/runner.py
l0n0lhttputils/token_mgr.py
l0n0lhttputils/util.py
l0n0lhttputils-1.2.3.dist-info/LICENSE
l0n0lhttputils-1.2.3.dist-info/METADATA
l0n0lhttputils-1.2.3.dist-info/WHEEL
l0n0lhttputils-1.2.3.dist-info/top_level.txt
l0n0lhttputils-1.2.3.dist-info/RECORD
