Metadata-Version: 2.1
Name: l0n0lhttputils
Version: 1.2.3
Summary: 平时常用的http server|mysql|配置文件
Home-page: https://gitee.com/l00n00l/http_server_utils
Author: l0n0l
Author-email: 1038352856@qq.com
License: UNKNOWN
Platform: UNKNOWN
Classifier: Programming Language :: Python :: 3
Classifier: License :: OSI Approved :: GNU General Public License (GPL)
Classifier: Operating System :: OS Independent
Requires-Dist: pymysql
Requires-Dist: aiohttp[speedups]
Requires-Dist: requests
Requires-Dist: pyyaml
Requires-Dist: xlrd
